kdparser/__init__.py
kdparser/jsonParser.py
kdparser/xmlParser.py
kdparser-0.2.2.dist-info/METADATA
kdparser-0.2.2.dist-info/WHEEL
kdparser-0.2.2.dist-info/top_level.txt
kdparser-0.2.2.dist-info/RECORD
