Metadata-Version: 2.1
Name: kdparser
Version: 0.2.2
Summary: A python library to parse files easily
Home-page: UNKNOWN
Author: Dor Dvir-Raviv, Kobi Shabaton
License: MIT
Keywords: python,parsing,json,xml,yaml,parse
Platform: UNKNOWN
